pytest_duration_insights/__init__.py
pytest_duration_insights/__main__.py
pytest_duration_insights/_parsing.py
pytest_duration_insights/static/data.json
pytest_duration_insights/static/favicon.png
pytest_duration_insights/static/global.css
pytest_duration_insights/static/index.html
pytest_duration_insights/static/treedata.json
pytest_duration_insights/static/build/bundle.css
pytest_duration_insights/static/build/bundle.js
pytest_duration_insights/static/build/bundle.js.map
pytest_duration_insights-0.1.2.dist-info/METADATA
pytest_duration_insights-0.1.2.dist-info/WHEEL
pytest_duration_insights-0.1.2.dist-info/entry_points.txt
pytest_duration_insights-0.1.2.dist-info/top_level.txt
pytest_duration_insights-0.1.2.dist-info/RECORD
