Metadata-Version: 2.1
Name: pytest-duration-insights
Version: 0.1.2
Project-URL: Bug Tracker, https://github.com/koaning/pytest-duration-insights/issues
Project-URL: Documentation, https://github.com/koaning/pytest-duration-insights
Project-URL: Source Code, https://github.com/koaning/pytest-duration-insights
Classifier: Intended Audience :: Developers
Classifier: Programming Language :: Python :: 3
Classifier: Programming Language :: Python :: 3.7
Classifier: Programming Language :: Python :: 3.8
Classifier: Programming Language :: Python :: 3.9
Classifier: License :: OSI Approved :: MIT License
Requires-Dist: pytest-reportlog >=0.1.2
Requires-Dist: clumper >=0.2.12
Requires-Dist: parse >=1.19.0
Requires-Dist: typer >=0.3.2
